License.md
MANIFEST.in
Readme.md
setup.py
qrogue/__init__.py
qrogue/qrogue.py
qrogue.egg-info/PKG-INFO
qrogue.egg-info/SOURCES.txt
qrogue.egg-info/dependency_links.txt
qrogue.egg-info/entry_points.txt
qrogue.egg-info/requires.txt
qrogue.egg-info/top_level.txt
qrogue/data/fresh.qrsave
qrogue/data/qrogue_launch.config
qrogue/data/dungeons/l0exam.qrdg
qrogue/data/dungeons/l0k0v0.qrdg
qrogue/data/dungeons/l0k0v1.qrdg
qrogue/data/dungeons/l0k0v2.qrdg
qrogue/data/dungeons/l0k0v3.qrdg
qrogue/data/dungeons/l0k0v4.qrdg
qrogue/data/dungeons/l0k0v5.qrdg
qrogue/data/dungeons/l0k0v6.qrdg
qrogue/data/dungeons/l0k1v0.qrdg
qrogue/data/dungeons/l0k1v1.qrdg
qrogue/data/dungeons/l0k1v2.qrdg
qrogue/data/dungeons/l0k1v3.qrdg
qrogue/data/dungeons/l0k1v4.qrdg
qrogue/data/dungeons/l0k1v5.qrdg
qrogue/data/dungeons/l0k1v6.qrdg
qrogue/data/dungeons/l0training.qrdg
qrogue/data/dungeons/wfc_rooms0 - Kopie.qrdg
qrogue/data/dungeons/wfc_rooms0.qrdg
qrogue/game/__init__.py
qrogue/game/target_difficulty.py
qrogue/game/target_factory.py
qrogue/game/logic/__init__.py
qrogue/game/logic/message.py
qrogue/game/logic/puzzle_generator.py
qrogue/game/logic/actors/__init__.py
qrogue/game/logic/actors/controllables/__init__.py
qrogue/game/logic/actors/controllables/controllable.py
qrogue/game/logic/actors/controllables/qubit.py
qrogue/game/logic/actors/controllables/robot.py
qrogue/game/logic/actors/puzzles/__init__.py
qrogue/game/logic/actors/puzzles/boss.py
qrogue/game/logic/actors/puzzles/challenge.py
qrogue/game/logic/actors/puzzles/enemy.py
qrogue/game/logic/actors/puzzles/fusion_target.py
qrogue/game/logic/actors/puzzles/riddle.py
qrogue/game/logic/actors/puzzles/target.py
qrogue/game/logic/base/__init__.py
qrogue/game/logic/base/circuit_matrix.py
qrogue/game/logic/base/simulator.py
qrogue/game/logic/base/state_vector.py
qrogue/game/logic/collectibles/__init__.py
qrogue/game/logic/collectibles/collectible.py
qrogue/game/logic/collectibles/collectible_factory.py
qrogue/game/logic/collectibles/instruction.py
qrogue/game/logic/collectibles/pickup.py
qrogue/game/logic/collectibles/special_items.py
qrogue/game/world/__init__.py
