Metadata-Version: 2.1
Name: qrogue
Version: 1.0
Summary: QRogue is an educational Quantum Computing puzzle game inspired by the classical game Rogue.
Home-page: https://github.com/7Magic7Mike7/Qrogue
Author: Michael Artner
Author-email: michael.artner@hotmail.de
License: MIT
Download-URL: https://github.com/7Magic7Mike7/Qrogue/releases/tag/1.0
Keywords: Quantum Computing,Gamification,Video Game,PyCUI
Platform: UNKNOWN
Classifier: Development Status :: 5 - Production/Stable
Classifier: Intended Audience :: Education
Classifier: Intended Audience :: Science/Research
Classifier: Topic :: Games/Entertainment :: Puzzle Games
Classifier: Programming Language :: Python :: 3.8
